gemini_assistant/__init__.py
gemini_assistant-0.1.0.dist-info/METADATA
gemini_assistant-0.1.0.dist-info/WHEEL
gemini_assistant-0.1.0.dist-info/top_level.txt
gemini_assistant-0.1.0.dist-info/RECORD
