Metadata-Version: 2.4
Name: gemini_assistant
Version: 0.1.0
Summary: A helper library for integrating the Google Gemini API into web applications.
Home-page: https://github.com/fars-a/gemini_assistant
Author: Farsan Suneer
Author-email: farsansuneer@gmail.com
Classifier: Programming Language :: Python :: 3
Classifier: License :: OSI Approved :: MIT License
Classifier: Operating System :: OS Independent
Requires-Python: >=3.8
Requires-Dist: google-genai
Dynamic: author
Dynamic: author-email
Dynamic: classifier
Dynamic: description
Dynamic: description-content-type
Dynamic: home-page
Dynamic: requires-dist
Dynamic: requires-python
Dynamic: summary
